pyvagrantfile/Parser.py
pyvagrantfile/__init__.py
pyvagrantfile-0.5.11.dist-info/DESCRIPTION.rst
pyvagrantfile-0.5.11.dist-info/METADATA
pyvagrantfile-0.5.11.dist-info/RECORD
pyvagrantfile-0.5.11.dist-info/WHEEL
pyvagrantfile-0.5.11.dist-info/metadata.json
pyvagrantfile-0.5.11.dist-info/top_level.txt
