Metadata-Version: 2.0
Name: pyvagrantfile
Version: 0.5.11
Summary: Parser to extract data from a Vagrantfile into a data struct readable by python
Home-page: https://github.com/drewsonne/pyvagrantfile
Author: Drew J. Sonne
Author-email: drew.sonne@gmail.com
License: UNKNOWN
Download-URL: https://github.com/drewsonne/pyvagrantfile/archive/0.5.11.tar.gz
Keywords: vagrant,parser,ruby
Platform: UNKNOWN
Classifier: Development Status :: 4 - Beta
Classifier: Intended Audience :: Developers
Classifier: Intended Audience :: Information Technology
Classifier: License :: OSI Approved :: GNU General Public License v2 (GPLv2)
Classifier: Natural Language :: English
Classifier: Programming Language :: Python
Classifier: Programming Language :: Python :: 2
Classifier: Programming Language :: Python :: 2.6
Classifier: Programming Language :: Python :: 2.7
Classifier: Programming Language :: Python :: 3
Classifier: Programming Language :: Python :: 3.0
Classifier: Programming Language :: Python :: 3.1
Classifier: Programming Language :: Python :: 3.2
Classifier: Programming Language :: Python :: 3.3
Classifier: Programming Language :: Python :: 3.4
Classifier: Programming Language :: Python :: 3.5
Classifier: Operating System :: POSIX
Classifier: Operating System :: POSIX :: Linux
Classifier: Operating System :: MacOS :: MacOS X
Classifier: Topic :: Software Development
Classifier: Topic :: System :: Installation/Setup
Requires-Dist: six
